full-adder/verilog/full_adder.v
module full_adder
(
  input wire i_x, i_y, i_carry,
  output wire o_sum, o_carry
);

  assign o_sum = i_x ^ i_y ^ i_carry;
  assign o_carry = i_x & i_y | (i_x ^ i_y) & i_carry;

endmodule

full-adder/verilog/full_adder_tb.v
`include "full_adder.v"
`timescale 1 ns/10 ps  // time-unit = 1 ns, precision = 10 ps

module full_adder_tb;

  reg x, y, c;
  wire sum, o_carry;

  localparam period = 20;  

  full_adder adder_inst (
    .i_x(x),
    .i_y(y),
    .i_carry(c),
    .o_sum(sum),
    .o_carry(o_carry)
  );
 
  initial
    begin
      $dumpfile("../build/test.vcd");
      $dumpvars(1, full_adder_tb);
      x = 0; y = 0; c = 0; #period; 
      x = 0; y = 0; c = 1; #period;
      x = 0; y = 1; c = 0; #period; 
      x = 0; y = 1; c = 1; #period; 
      x = 1; y = 0; c = 0; #period; 
      x = 1; y = 0; c = 1; #period; 
      x = 1; y = 1; c = 0; #period; 
      x = 1; y = 1; c = 1; #period; 
    end 

  // initial begin
  //   		 $monitor("x=%b,y=%b,c=%b,oS=%b,oC=%b \n",x,y,c,sum,o_carry );
  // end
endmodule

full-adder/verilog/test_bench.vcd
$date
	Sat May 29 16:29:40 2021
$end
$version
	Icarus Verilog
$end
$timescale
	10ps
$end
$scope module full_adder_tb $end
$var wire 1 ! sum $end
$var wire 1 " o_carry $end
$var reg 1 # c $end
$var reg 1 $ x $end
$var reg 1 % y $end
$upscope $end
$enddefinitions $end
#0
$dumpvars
0%
0$
0#
0"
0!
$end
#2000
1!
1#
#4000
0#
1%
#6000
1"
0!
1#
#8000
0"
1!
0#
0%
1$
#10000
1"
0!
1#
#12000
0#
1%
#14000
1!
1#
