verilog-FA/full_adder.v
module full_adder 
(
  input wire i_x, i_y, i_carry,
  output wire o_sum, o_carry
);

  assign o_sum = i_x ^ i_y ^ i_carry;
  assign o_carry = i_x & i_y | (i_x ^ i_y) & i_carry;

endmodule

fa-vsim/full_adder_synth_tb.v
// `include "../libs/freepdk-45nm/stdcells.v"
`include "osu018_stdcells.v"
`include "full_adder.v"
`timescale 1 ns/10 ps  // time-unit = 1 ns, precision = 10 ps

module full_adder_tb;

  reg x, y, c;
  wire sum, o_carry;

  localparam period = 20;  

  full_adder adder_inst (
    .i_x(x),
    .i_y(y),
    .i_carry(c),
    .o_sum(sum),
    .o_carry(o_carry)
  );
    

  initial
    begin
      //$sdf_annotate("./build/full_adder.sdf", adder_inst,,"sdfAnnotateLog.log"); 
      $dumpfile("test_bench.vcd");
      $dumpvars(1, full_adder_tb);
      // $dumpvars(1, adder_inst);
      x = 0; y = 0; c = 0; #period; 
      x = 0; y = 0; c = 1; #period;
      x = 0; y = 1; c = 0; #period; 
      x = 0; y = 1; c = 1; #period; 
      x = 1; y = 0; c = 0; #period; 
      x = 1; y = 0; c = 1; #period; 
      x = 1; y = 1; c = 0; #period; 
      x = 1; y = 1; c = 1; #period; 
    end 
    
endmodule

fa-vsim/test_bench.vcd
$date
	Mon Jun 14 20:30:17 2021
$end
$version
	ModelSim Version 2021.1
$end
$timescale
	10ps
$end

$scope module full_adder_tb $end
$var parameter 32 ! period $end
$var reg 1 " x $end
$var reg 1 # y $end
$var reg 1 $ c $end
$var wire 1 % sum $end
$var wire 1 & o_carry $end
$upscope $end
$enddefinitions $end
#0
$dumpvars
0"
0#
0$
b10100 !
x%
x&
$end
#18
0&
#26
0%
#2000
1$
#2017
1%
#4000
1#
0$
#4017
0%
#4025
1%
#6000
1$
#6017
1&
#6023
0%
#8000
1"
0#
0$
#8017
0&
#8021
1%
#10000
1$
#10017
1&
#10023
0%
#12000
1#
0$
#14000
1$
#14017
1%
